imgenx/factory.py
imgenx/main.py
imgenx/operator.py
imgenx/script.py
imgenx/server.py
imgenx/utils.py
imgenx/predictor/base/base_image_inspector.py
imgenx/predictor/base/base_image_to_image.py
imgenx/predictor/base/base_image_to_video.py
imgenx/predictor/base/base_text_to_image.py
imgenx/predictor/base/base_text_to_video.py
imgenx/predictor/generators/aliyun/image_inspector.py
imgenx/predictor/generators/aliyun/image_to_image.py
imgenx/predictor/generators/aliyun/image_to_video.py
imgenx/predictor/generators/aliyun/text_to_image.py
imgenx/predictor/generators/aliyun/text_to_video.py
imgenx/predictor/generators/doubao/image_inspector.py
imgenx/predictor/generators/doubao/image_to_image.py
imgenx/predictor/generators/doubao/image_to_video.py
imgenx/predictor/generators/doubao/text_to_image.py
imgenx/predictor/generators/doubao/text_to_video.py
imgenx-0.3.0.dist-info/licenses/LICENSE
imgenx-0.3.0.dist-info/METADATA
imgenx-0.3.0.dist-info/WHEEL
imgenx-0.3.0.dist-info/entry_points.txt
imgenx-0.3.0.dist-info/top_level.txt
imgenx-0.3.0.dist-info/RECORD
