Metadata-Version: 2.4
Name: imgenx
Version: 0.3.0
Summary: AI 图片/视频生成与处理套件，支持文本/图生图、文本/图生视频、图片分析与常用编辑（裁剪、缩放、转换、调参），可作为命令行工具或 MCP Server 使用
Project-URL: repository, https://github.com/NewToolAI/imgenx
Requires-Python: >=3.10
License-File: LICENSE
Requires-Dist: fastmcp>=2.12.4
Requires-Dist: python-dotenv>=1.1.1
Requires-Dist: volcengine-python-sdk[ark]>=4.0.22
Requires-Dist: requests>=2.25.0
Requires-Dist: pillow>=12.0.0
Requires-Dist: dashscope>=1.25.1
Dynamic: license-file
